tri4plads/__init__.py
tri4plads/generate_analysis/__init__.py
tri4plads/generate_analysis/db_queries.py
tri4plads/generate_analysis/interactive_cli.py
tri4plads/generate_analysis/main.py
tri4plads-0.1.1.dist-info/LICENSE
tri4plads-0.1.1.dist-info/METADATA
tri4plads-0.1.1.dist-info/WHEEL
tri4plads-0.1.1.dist-info/RECORD
