Metadata-Version: 2.1
Name: tri4plads
Version: 0.1.1
Summary: Basic code to obtain probability distribution functions for EoL using TRI data
Author: Jose D. Hernandez-Betancur
Author-email: jodhernandezbemj@gmail.com
Requires-Python: >=3.12,<3.13
Classifier: Programming Language :: Python :: 3
Classifier: Programming Language :: Python :: 3.12
Requires-Dist: aiohttp (>=3.10.10,<4.0.0)
Requires-Dist: alembic (>=1.13.3,<2.0.0)
Requires-Dist: hydra-core (>=1.3.2,<2.0.0)
Requires-Dist: omegaconf (>=2.3.0,<3.0.0)
Requires-Dist: openpyxl (>=3.1.5,<4.0.0)
Requires-Dist: pandas (>=2.1.4,<3.0.0)
Requires-Dist: pandas-stubs (>=2.2.3.241009,<3.0.0.0)
Requires-Dist: pgmpy (>=0.1.26,<0.2.0)
Requires-Dist: pip (>=24.3.1,<25.0.0)
Requires-Dist: poetry (>=1.8.4,<2.0.0)
Requires-Dist: python-dotenv (>=1.0.1,<2.0.0)
Requires-Dist: questionary (>=2.0.1,<3.0.0)
Requires-Dist: rich (>=13.9.4,<14.0.0)
Requires-Dist: sqlalchemy (>=2.0.36,<3.0.0)
Requires-Dist: typing (>=3.7.4.3,<4.0.0.0)
